tests/__init__.py
tests/base.py
tests/test_projects.py
tests/test_version.py
wistia_py/__init__.py
wistia_py/mock.py
wistia_py/wrapper.py
wistia_py-0.1.1.dist-info/METADATA
wistia_py-0.1.1.dist-info/RECORD
wistia_py-0.1.1.dist-info/WHEEL
wistia_py-0.1.1.dist-info/entry_points.txt
wistia_py-0.1.1.dist-info/top_level.txt
